rlaehgus97_lotto/__init__.py
rlaehgus97_lotto/draw.py
rlaehgus97_lotto-0.2.0.dist-info/METADATA
rlaehgus97_lotto-0.2.0.dist-info/WHEEL
rlaehgus97_lotto-0.2.0.dist-info/top_level.txt
rlaehgus97_lotto-0.2.0.dist-info/RECORD
