Metadata-Version: 2.1
Name: rlaehgus97_lotto
Version: 0.2.0
Summary: Default template for PDM package
Author-email: rlaehgus97 <starkim625@gmail.com>
License: MIT
Requires-Python: >=3.9
